boursika/__init__.py
boursika/config.py
boursika/enums.py
boursika/errors.py
boursika/predictors.py
boursika/providers.py
boursika/utils/__init__.py
boursika/utils/date_helpers.py
boursika-1.2.0.dist-info/LICENSE
boursika-1.2.0.dist-info/WHEEL
boursika-1.2.0.dist-info/METADATA
boursika-1.2.0.dist-info/RECORD
