Metadata-Version: 2.1
Name: boursika
Version: 1.2.0
Summary: client for boursika-engine platform
Home-page: http://docs.boursika-engine.ir
License: MIT
Author: Mahdi Sadeghi
Author-email: mail2mahsad@gmail.com
Requires-Python: >=3.8,<4.0
Classifier: License :: OSI Approved :: MIT License
Classifier: Programming Language :: Python :: 3
Classifier: Programming Language :: Python :: 3.10
Classifier: Programming Language :: Python :: 3.8
Classifier: Programming Language :: Python :: 3.9
Requires-Dist: jdatetime (>=3,<4)
Requires-Dist: pandas (>=1,<2)
Requires-Dist: python-dateutil (>=2,<3)
Requires-Dist: requests (>=2,<3)
Requires-Dist: websocket-client (>=1,<2)
Project-URL: Documentation, http://docs.boursika-engine.ir
